chatlab/__init__.py
chatlab/_version.py
chatlab/builtins/__init__.py
chatlab/chat.py
chatlab/components/function_details.py
chatlab/decorators.py
chatlab/errors.py
chatlab/messaging.py
chatlab/models.py
chatlab/prompts.py
chatlab/py.typed
chatlab/registry.py
chatlab/tools/__init__.py
chatlab/tools/_mediatypes.py
chatlab/tools/colors.py
chatlab/tools/files.py
chatlab/tools/python.py
chatlab/tools/shell.py
chatlab/views/__init__.py
chatlab/views/assistant.py
chatlab/views/tools.py
chatlab-2.1.1.dist-info/LICENSE
chatlab-2.1.1.dist-info/METADATA
chatlab-2.1.1.dist-info/WHEEL
chatlab-2.1.1.dist-info/RECORD
