Metadata-Version: 2.1
Name: chatlab
Version: 2.1.1
Summary: Chat Plugin Experiments, Simplified. Give all the power to the models in your life.
Home-page: https://github.com/rgbkrk/chatlab
License: BSD-3-Clause
Author: Kyle Kelley
Author-email: rgbkrk@gmail.com
Requires-Python: >=3.10,<4.0
Classifier: Development Status :: 3 - Alpha
Classifier: Framework :: Jupyter
Classifier: Framework :: Jupyter :: JupyterLab
Classifier: Intended Audience :: Developers
Classifier: Intended Audience :: Education
Classifier: Intended Audience :: Science/Research
Classifier: License :: OSI Approved :: BSD License
Classifier: Natural Language :: English
Classifier: Programming Language :: Python :: 3
Classifier: Programming Language :: Python :: 3.10
Classifier: Programming Language :: Python :: 3.11
Classifier: Programming Language :: Python :: 3.12
Classifier: Programming Language :: Python :: 3.9
Classifier: Topic :: Communications :: Chat
Classifier: Topic :: Scientific/Engineering :: Artificial Intelligence
Classifier: Topic :: Scientific/Engineering :: Artificial Life
Classifier: Topic :: Scientific/Engineering :: Human Machine Interfaces
Provides-Extra: dev
Provides-Extra: test
Requires-Dist: aiofiles (>=23.1.0,<24.0.0)
Requires-Dist: deprecation (>=2.1.0,<3.0.0)
Requires-Dist: instructor (>=0.6.1,<0.7.0)
Requires-Dist: ipython (>=7.0.0)
Requires-Dist: mypy (>=1.6.1,<2.0.0) ; extra == "test"
Requires-Dist: openai (>=1.2.2,<2.0.0)
Requires-Dist: pydantic (>=2.4.2,<3.0.0)
Requires-Dist: python-ulid (>=1.1.0,<2.0.0)
Requires-Dist: repr-llm (>=0.2.0,<0.3.0)
Requires-Dist: spork (>=1.2.0,<2.0.0)
Requires-Dist: types-aiofiles (>=23.2.0.0,<24.0.0.0)
Requires-Dist: typing-extensions (>=4.7.1,<5.0.0)
Requires-Dist: vdom (>=1.0.0,<2.0.0)
